{
	"format_version": "1.8.0",
	"animations": {
		"owl.flying": {
			"loop": true,
			"animation_length": 1.33333,
			"bones": {
				"owl": {
					"rotation": {
						"0.0": {
							"vector": [15, 0, 0]
						},
						"0.6667": {
							"vector": ["7.5+math.cos(query.anim_time*40)90*", 0, 0]
						},
						"1.3333": {
							"vector": [15, 0, 0]
						}
					},
					"position": {
						"0.0": {
							"vector": [0, 0, 0]
						},
						"0.6667": {
							"vector": [0, 0.4, 0]
						},
						"1.3333": {
							"vector": [0, 0, 0]
						}
					}
				},
				"lwing": {
					"rotation": {
						"0.0": {
							"vector": [0, 0, 0]
						},
						"0.6667": {
							"vector": [0, 0, "-45+math.cos(query.anim_time*40)90*"]
						},
						"1.3333": {
							"vector": [0, 0, 0]
						}
					},
					"position": {
						"0.0": {
							"vector": [0, 0, 0]
						},
						"0.6667": {
							"vector": [0, -0.3, 0]
						},
						"1.3333": {
							"vector": [0, 0, 0]
						}
					}
				},
				"rwing": {
					"rotation": {
						"0.0": {
							"vector": [0, 0, 0]
						},
						"0.6667": {
							"vector": [0, 0, "45+math.cos(query.anim_time*40)90*"]
						},
						"1.3333": {
							"vector": [0, 0, 0]
						}
					},
					"position": {
						"0.0": {
							"vector": [0, 0, 0]
						},
						"0.6667": {
							"vector": [0, -0.3, 0]
						},
						"1.3333": {
							"vector": [0, 0, 0]
						}
					}
				},
				"lleg": {
					"rotation": {
						"0.0": {
							"vector": [0, 0, 0]
						},
						"0.6667": {
							"vector": ["10+math.cos(query.anim_time*50)90*", 0, 0]
						},
						"1.3333": {
							"vector": [0, 0, 0]
						}
					}
				},
				"rleg": {
					"rotation": {
						"0.0": {
							"vector": [0, 0, 0]
						},
						"0.6667": {
							"vector": ["-10+math.cos(query.anim_time*50)90*", 0, 0]
						},
						"1.3333": {
							"vector": [0, 0, 0]
						}
					}
				}
			}
		},
		"owl.idle": {
			"loop": true
		},
		"owl.walk": {
			"loop": true,
			"animation_length": 0.95833,
			"bones": {
				"owl": {
					"rotation": {
						"0.0": {
							"vector": [0, 0, -5]
						},
						"0.5": {
							"vector": [0, 0, 2.5]
						},
						"0.9583": {
							"vector": [0, 0, -5]
						}
					}
				},
				"body": {
					"rotation": {
						"0.0": {
							"vector": [-2.5, 0, 0]
						},
						"0.5": {
							"vector": [5, 0, 0]
						},
						"0.9583": {
							"vector": [-2.5, 0, 0]
						}
					}
				}
			}
		}
	},
	"geckolib_format_version": 2
}